<?xml version="1.0" encoding="UTF-8"?><TED_EXPORT xmlns:xlink="http://www.w3.org/1999/xlink" xmlns:xsi="http://www.w3.org/2001/XMLSchema-instance" xmlns="http://publications.europa.eu/resource/schema/ted/R2.0.9/publication" xmlns:n2016="http://publications.europa.eu/resource/schema/ted/2016/nuts" xsi:schemaLocation="http://publications.europa.eu/resource/schema/ted/R2.0.9/publication TED_EXPORT.xsd" VERSION="R2.0.9.S03.E01" DOC_ID="426934-2019" EDITION="2019175"><TECHNICAL_SECTION><RECEPTION_ID>19-436843-001</RECEPTION_ID><DELETION_DATE>20191218</DELETION_DATE><FORM_LG_LIST>EN </FORM_LG_LIST><COMMENTS>From Convertor</COMMENTS></TECHNICAL_SECTION><LINKS_SECTION><XML_SCHEMA_DEFINITION_LINK xlink:type="simple" xlink:href="http://ted.europa.eu" xlink:title="TED WEBSITE"/><OFFICIAL_FORMS_LINK xlink:type="simple" xlink:href="http://ted.europa.eu"/><FORMS_LABELS_LINK xlink:type="simple" xlink:href="http://ted.europa.eu"/><ORIGINAL_CPV_LINK xlink:type="simple" xlink:href="http://ted.europa.eu"/><ORIGINAL_NUTS_LINK xlink:type="simple" xlink:href="http://ted.europa.eu"/></LINKS_SECTION><CODED_DATA_SECTION><REF_OJS><COLL_OJ>S</COLL_OJ><NO_OJ>175</NO_OJ><DATE_PUB>20190911</DATE_PUB></REF_OJS><NOTICE_DATA><NO_DOC_OJS>2019/S 175-426934</NO_DOC_OJS><URI_LIST><URI_DOC LG="EN">http://ted.europa.eu/udl?uri=TED:NOTICE:426934-2019:TEXT:EN:HTML</URI_DOC></URI_LIST><LG_ORIG>EN</LG_ORIG><ISO_COUNTRY VALUE="UK"/><IA_URL_GENERAL>www.bridgend.gov.uk</IA_URL_GENERAL><ORIGINAL_CPV CODE="34115200">Motor vehicles for the transport of fewer than 10 persons</ORIGINAL_CPV><n2016:PERFORMANCE_NUTS CODE="UKL17">Bridgend and Neath Port Talbot</n2016:PERFORMANCE_NUTS><n2016:CA_CE_NUTS CODE="UKL17">Bridgend and Neath Port Talbot</n2016:CA_CE_NUTS><n2016:TENDERER_NUTS CODE="UK">UNITED KINGDOM</n2016:TENDERER_NUTS><n2016:TENDERER_NUTS CODE="UKL17">Bridgend and Neath Port Talbot</n2016:TENDERER_NUTS><n2016:TENDERER_NUTS CODE="UKL">WALES</n2016:TENDERER_NUTS><VALUES><VALUE TYPE="PROCUREMENT_TOTAL" CURRENCY="GBP">1766796</VALUE></VALUES><REF_NOTICE><NO_DOC_OJS>2019/S 108-263245</NO_DOC_OJS></REF_NOTICE></NOTICE_DATA><CODIF_DATA><DS_DATE_DISPATCH>20190909</DS_DATE_DISPATCH><AA_AUTHORITY_TYPE CODE="3">Regional or local authority</AA_AUTHORITY_TYPE><TD_DOCUMENT_TYPE CODE="7">Contract award notice</TD_DOCUMENT_TYPE><NC_CONTRACT_NATURE CODE="4">Services</NC_CONTRACT_NATURE><PR_PROC CODE="1">Open procedure</PR_PROC><RP_REGULATION CODE="5">European Union, with participation by GPA countries</RP_REGULATION><TY_TYPE_BID CODE="9">Not applicable</TY_TYPE_BID><AC_AWARD_CRIT CODE="1">Lowest price</AC_AWARD_CRIT><MA_MAIN_ACTIVITIES CODE="S">General public services</MA_MAIN_ACTIVITIES><HEADING>01C03</HEADING><INITIATOR>01</INITIATOR></CODIF_DATA></CODED_DATA_SECTION><TRANSLATION_SECTION><ML_TITLES><ML_TI_DOC LG="BG"><TI_CY>Обединено кралство</TI_CY><TI_TOWN>Bridgend</TI_TOWN><TI_TEXT><P>Моторни превозни средства за превоз на по-малко от десет пътника</P></TI_TEXT></ML_TI_DOC><ML_TI_DOC LG="CS"><TI_CY>Spojené království/Velká Británie</TI_CY><TI_TOWN>Bridgend</TI_TOWN><TI_TEXT><P>Motorová vozidla pro přepravu méně než 10 lidí</P></TI_TEXT></ML_TI_DOC><ML_TI_DOC LG="DA"><TI_CY>Forenede Kongerige, Det</TI_CY><TI_TOWN>Bridgend</TI_TOWN><TI_TEXT><P>Motorkøretøjer til befordring af færre end 10 personer</P></TI_TEXT></ML_TI_DOC><ML_TI_DOC LG="DE"><TI_CY>das Vereinigte Königreich</TI_CY><TI_TOWN>Bridgend</TI_TOWN><TI_TEXT><P>Kraftfahrzeuge für den Transport von weniger als 10 Personen</P></TI_TEXT></ML_TI_DOC><ML_TI_DOC LG="EL"><TI_CY>Ηνωμένο Βασίλειο</TI_CY><TI_TOWN>Bridgend</TI_TOWN><TI_TEXT><P>Αυτοκίνητα οχήματα για τη μεταφορά κάτω των 10 ατόμων</P></TI_TEXT></ML_TI_DOC><ML_TI_DOC LG="EN"><TI_CY>United Kingdom</TI_CY><TI_TOWN>Bridgend</TI_TOWN><TI_TEXT><P>Motor vehicles for the transport of fewer than 10 persons</P></TI_TEXT></ML_TI_DOC><ML_TI_DOC LG="ES"><TI_CY>Reino Unido</TI_CY><TI_TOWN>Bridgend</TI_TOWN><TI_TEXT><P>Vehículos de motor para el transporte de menos de diez personas</P></TI_TEXT></ML_TI_DOC><ML_TI_DOC LG="ET"><TI_CY>Suurbritannia / Ühendkuningriik</TI_CY><TI_TOWN>Bridgend</TI_TOWN><TI_TEXT><P>Mootorsõidukid kuni 10 inimese veoks</P></TI_TEXT></ML_TI_DOC><ML_TI_DOC LG="FI"><TI_CY>Yhdistynyt kuningaskunta</TI_CY><TI_TOWN>Bridgend</TI_TOWN><TI_TEXT><P>Alle 10 henkilön kuljetukseen tarkoitetut moottoriajoneuvot</P></TI_TEXT></ML_TI_DOC><ML_TI_DOC LG="FR"><TI_CY>Royaume-Uni</TI_CY><TI_TOWN>Bridgend</TI_TOWN><TI_TEXT><P>Véhicules à moteur pour le transport de moins de dix personnes</P></TI_TEXT></ML_TI_DOC><ML_TI_DOC LG="GA"><TI_CY>Ríocht Aontaithe, an</TI_CY><TI_TOWN>Bridgend</TI_TOWN><TI_TEXT><P>Motor vehicles for the transport of fewer than 10 persons</P></TI_TEXT></ML_TI_DOC><ML_TI_DOC LG="HR"><TI_CY>Ujedinjena Kraljevina</TI_CY><TI_TOWN>Bridgend</TI_TOWN><TI_TEXT><P>Motorna vozila za prijevoz manje od 10 osoba</P></TI_TEXT></ML_TI_DOC><ML_TI_DOC LG="HU"><TI_CY>Egyesült Királyság</TI_CY><TI_TOWN>Bridgend</TI_TOWN><TI_TEXT><P>Gépjármű tíznél kevesebb személy szállítására</P></TI_TEXT></ML_TI_DOC><ML_TI_DOC LG="IT"><TI_CY>Regno Unito</TI_CY><TI_TOWN>Bridgend</TI_TOWN><TI_TEXT><P>Veicoli a motore per il trasporto di meno di dieci persone</P></TI_TEXT></ML_TI_DOC><ML_TI_DOC LG="LT"><TI_CY>Jungtinė Karalystė, Didžioji Britanija</TI_CY><TI_TOWN>Bridgend</TI_TOWN><TI_TEXT><P>Motorinės transporto priemonės, skirtos vežti mažiau kaip 10 žmonių</P></TI_TEXT></ML_TI_DOC><ML_TI_DOC LG="LV"><TI_CY>Apvienotā Karaliste</TI_CY><TI_TOWN>Bridgend</TI_TOWN><TI_TEXT><P>Mehāniskie transportlīdzekļi mazāk nekā 10 cilvēku pārvadāšanai</P></TI_TEXT></ML_TI_DOC><ML_TI_DOC LG="MT"><TI_CY>Ir-Renju Unit</TI_CY><TI_TOWN>Bridgend</TI_TOWN><TI_TEXT><P>Vetturi bil-magna għat-trasportazzjoni ta' anqas minn 10 persuni</P></TI_TEXT></ML_TI_DOC><ML_TI_DOC LG="NL"><TI_CY>Verenigd Koninkrijk</TI_CY><TI_TOWN>Bridgend</TI_TOWN><TI_TEXT><P>Motorvoertuigen voor personenvervoer van minder dan 10 personen</P></TI_TEXT></ML_TI_DOC><ML_TI_DOC LG="PL"><TI_CY>Zjednoczone Królestwo</TI_CY><TI_TOWN>Bridgend</TI_TOWN><TI_TEXT><P>Pojazdy silnikowe do transportu mniej niż 10 osób</P></TI_TEXT></ML_TI_DOC><ML_TI_DOC LG="PT"><TI_CY>Reino Unido</TI_CY><TI_TOWN>Bridgend</TI_TOWN><TI_TEXT><P>Veículos a motor para o transporte de menos de dez pessoas</P></TI_TEXT></ML_TI_DOC><ML_TI_DOC LG="RO"><TI_CY>Regatul Unit</TI_CY><TI_TOWN>Bridgend</TI_TOWN><TI_TEXT><P>Autovehicule pentru transportul a mai puţin de 10 persoane</P></TI_TEXT></ML_TI_DOC><ML_TI_DOC LG="SK"><TI_CY>Spojené kráľovstvo</TI_CY><TI_TOWN>Bridgend</TI_TOWN><TI_TEXT><P>Motorové vozidlá na prepravu menej než 10 osôb</P></TI_TEXT></ML_TI_DOC><ML_TI_DOC LG="SL"><TI_CY>Združeno kraljestvo</TI_CY><TI_TOWN>Bridgend</TI_TOWN><TI_TEXT><P>Motorna vozila za prevoz manj kot 10 oseb</P></TI_TEXT></ML_TI_DOC><ML_TI_DOC LG="SV"><TI_CY>Förenade kungariket</TI_CY><TI_TOWN>Bridgend</TI_TOWN><TI_TEXT><P>Motorfordon för transport av färre än tio personer</P></TI_TEXT></ML_TI_DOC></ML_TITLES><ML_AA_NAMES><AA_NAME LG="EN">Bridgend County Borough Council</AA_NAME></ML_AA_NAMES></TRANSLATION_SECTION><FORM_SECTION><NOTICE_UUID>d698aa84-5d64-41cf-a819-eaba5ef915fa</NOTICE_UUID><F03_2014 CATEGORY="ORIGINAL" FORM="F03" LG="EN"><LEGAL_BASIS VALUE="32014L0024"/><CONTRACTING_BODY><ADDRESS_CONTRACTING_BODY><OFFICIALNAME>Bridgend County Borough Council</OFFICIALNAME><ADDRESS>Bridgend County Borough Council, Procurement Unit, Civic Offices, Angel Street</ADDRESS><TOWN>Bridgend</TOWN><POSTAL_CODE>CF31 4WB</POSTAL_CODE><COUNTRY VALUE="UK"/><CONTACT_POINT>Jo Protheroe</CONTACT_POINT><PHONE>+44 1656642596</PHONE><E_MAIL>Jo.Protheroe1@bridgend.gov.uk</E_MAIL><n2016:NUTS CODE="UKL17"/><URL_GENERAL>www.bridgend.gov.uk</URL_GENERAL><URL_BUYER>https://www.sell2wales.gov.wales/search/Search_AuthProfile.aspx?ID=AA0417</URL_BUYER></ADDRESS_CONTRACTING_BODY><CENTRAL_PURCHASING/><CA_TYPE VALUE="REGIONAL_AUTHORITY"/><CA_ACTIVITY VALUE="GENERAL_PUBLIC_SERVICES"/></CONTRACTING_BODY><OBJECT_CONTRACT><TITLE><P>Provision of Home to School Transport Service via Taxis and Minibuses for Bridgend Council</P></TITLE><REFERENCE_NUMBER>B635</REFERENCE_NUMBER><CPV_MAIN><CPV_CODE CODE="34115200"/></CPV_MAIN><TYPE_CONTRACT CTYPE="SERVICES"/><SHORT_DESCR><P>Provision of home to school transport service via taxis and minibuses for Bridgend County Borough Council — various routes.</P></SHORT_DESCR><VAL_TOTAL CURRENCY="GBP">1766796</VAL_TOTAL><NO_LOT_DIVISION/><OBJECT_DESCR ITEM="1"><CPV_ADDITIONAL><CPV_CODE CODE="34115200"/></CPV_ADDITIONAL><n2016:NUTS CODE="UKL17"/><MAIN_SITE><P>Various educational establishments across Bridgend County Borough Council.</P></MAIN_SITE><SHORT_DESCR><P>Various routes for home to school transport via mini buses and taxis across Bridgend County Borough Council.</P></SHORT_DESCR><AC><AC_PRICE/></AC><NO_OPTIONS/><NO_EU_PROGR_RELATED/></OBJECT_DESCR></OBJECT_CONTRACT><PROCEDURE><PT_OPEN/><CONTRACT_COVERED_GPA/><NOTICE_NUMBER_OJ>2019/S 108-263245</NOTICE_NUMBER_OJ></PROCEDURE><AWARD_CONTRACT ITEM="1"><AWARDED_CONTRACT><DATE_CONCLUSION_CONTRACT>2019-09-02</DATE_CONCLUSION_CONTRACT><TENDERS><NB_TENDERS_RECEIVED>19</NB_TENDERS_RECEIVED><NB_TENDERS_RECEIVED_SME>19</NB_TENDERS_RECEIVED_SME><NB_TENDERS_RECEIVED_OTHER_EU>0</NB_TENDERS_RECEIVED_OTHER_EU><NB_TENDERS_RECEIVED_NON_EU>0</NB_TENDERS_RECEIVED_NON_EU><NB_TENDERS_RECEIVED_EMEANS>19</NB_TENDERS_RECEIVED_EMEANS></TENDERS><CONTRACTORS><AWARDED_TO_GROUP/><CONTRACTOR><ADDRESS_CONTRACTOR><OFFICIALNAME>Dan's Taxis</OFFICIALNAME><ADDRESS>91 Clos Tyn Y Coed, Sarn</ADDRESS><TOWN>Bridgend</TOWN><POSTAL_CODE>CF32 9NQ</POSTAL_CODE><COUNTRY VALUE="UK"/><n2016:NUTS CODE="UK"/></ADDRESS_CONTRACTOR><SME/></CONTRACTOR><CONTRACTOR><ADDRESS_CONTRACTOR><OFFICIALNAME>Peyton Travel Ltd</OFFICIALNAME><ADDRESS>Main avenue, Brackla Industrial Estate</ADDRESS><TOWN>Bridgend</TOWN><POSTAL_CODE>CF312AG</POSTAL_CODE><COUNTRY VALUE="UK"/><n2016:NUTS CODE="UKL17"/></ADDRESS_CONTRACTOR><SME/></CONTRACTOR><CONTRACTOR><ADDRESS_CONTRACTOR><OFFICIALNAME>James Taxis</OFFICIALNAME><ADDRESS>3 Vernon Road</ADDRESS><TOWN>Porthcawl</TOWN><POSTAL_CODE>CF36 5LN</POSTAL_CODE><COUNTRY VALUE="UK"/><n2016:NUTS CODE="UK"/></ADDRESS_CONTRACTOR><SME/></CONTRACTOR><CONTRACTOR><ADDRESS_CONTRACTOR><OFFICIALNAME>Village Bus and Taxi Ltd</OFFICIALNAME><ADDRESS>71 Bridgend road, Aberkenfig</ADDRESS><TOWN>Bridgend</TOWN><POSTAL_CODE>CF329AY</POSTAL_CODE><COUNTRY VALUE="UK"/><n2016:NUTS CODE="UK"/></ADDRESS_CONTRACTOR><SME/></CONTRACTOR><CONTRACTOR><ADDRESS_CONTRACTOR><OFFICIALNAME>Denway Travel</OFFICIALNAME><ADDRESS>10 Y Llest, Pen-y-Fai</ADDRESS><TOWN>Bridgend</TOWN><POSTAL_CODE>CF31 4NA</POSTAL_CODE><COUNTRY VALUE="UK"/><n2016:NUTS CODE="UK"/></ADDRESS_CONTRACTOR><SME/></CONTRACTOR><CONTRACTOR><ADDRESS_CONTRACTOR><OFFICIALNAME>Taxi Bridgend</OFFICIALNAME><ADDRESS>59 Pil-y-Cynffig, North Cornelly</ADDRESS><TOWN>Bridgend</TOWN><POSTAL_CODE>CF33 4NR</POSTAL_CODE><COUNTRY VALUE="UK"/><n2016:NUTS CODE="UKL17"/></ADDRESS_CONTRACTOR><SME/></CONTRACTOR><CONTRACTOR><ADDRESS_CONTRACTOR><OFFICIALNAME>Dragon Taxis</OFFICIALNAME><ADDRESS>25 Market Street</ADDRESS><TOWN>Bridgend</TOWN><POSTAL_CODE>CF31 1LJ</POSTAL_CODE><COUNTRY VALUE="UK"/><n2016:NUTS CODE="UKL"/></ADDRESS_CONTRACTOR><SME/></CONTRACTOR><CONTRACTOR><ADDRESS_CONTRACTOR><OFFICIALNAME>Driven Minibuses and Taxis</OFFICIALNAME><ADDRESS>8 Dock Street</ADDRESS><TOWN>Porthcawl</TOWN><POSTAL_CODE>CF36 3BL</POSTAL_CODE><COUNTRY VALUE="UK"/><n2016:NUTS CODE="UK"/></ADDRESS_CONTRACTOR><SME/></CONTRACTOR><CONTRACTOR><ADDRESS_CONTRACTOR><OFFICIALNAME>Forge Travel Ltd</OFFICIALNAME><ADDRESS>Forge Travel Ltd, 50 Pond MAWR Garth</ADDRESS><TOWN>Maesteg</TOWN><POSTAL_CODE>CF34 0NG</POSTAL_CODE><COUNTRY VALUE="UK"/><n2016:NUTS CODE="UKL17"/></ADDRESS_CONTRACTOR><SME/></CONTRACTOR><CONTRACTOR><ADDRESS_CONTRACTOR><OFFICIALNAME>Munro's Taxi and Minibus</OFFICIALNAME><ADDRESS>3 The Moulders, Aberkenfig</ADDRESS><TOWN>Bridgend</TOWN><POSTAL_CODE>CF32 9AH</POSTAL_CODE><COUNTRY VALUE="UK"/><n2016:NUTS CODE="UKL17"/></ADDRESS_CONTRACTOR><SME/></CONTRACTOR><CONTRACTOR><ADDRESS_CONTRACTOR><OFFICIALNAME>G AND S Travel</OFFICIALNAME><ADDRESS>unit 11 Penllwyngwent, Industrial Estate Ogmore Vale</ADDRESS><TOWN>Bridgend</TOWN><POSTAL_CODE>CF327AX</POSTAL_CODE><COUNTRY VALUE="UK"/><n2016:NUTS CODE="UKL17"/></ADDRESS_CONTRACTOR><SME/></CONTRACTOR><CONTRACTOR><ADDRESS_CONTRACTOR><OFFICIALNAME>Dial a Cab Taxi and Minibus Service</OFFICIALNAME><ADDRESS>5 Adams avenue, Bryncethin</ADDRESS><TOWN>Bridgend</TOWN><POSTAL_CODE>CF32 9RX</POSTAL_CODE><COUNTRY VALUE="UK"/><n2016:NUTS CODE="UKL17"/></ADDRESS_CONTRACTOR><SME/></CONTRACTOR></CONTRACTORS><VALUES><VAL_TOTAL CURRENCY="GBP">1766796</VAL_TOTAL></VALUES></AWARDED_CONTRACT></AWARD_CONTRACT><COMPLEMENTARY_INFO><INFO_ADD><P>(WA Ref:95464)</P></INFO_ADD><ADDRESS_REVIEW_BODY><OFFICIALNAME>Bridgend County Borough Council</OFFICIALNAME><ADDRESS>Bridgend County Borough Council, Procurement Unit, Civic Offices, Angel Street</ADDRESS><TOWN>Bridgend</TOWN><POSTAL_CODE>CF31 4WB</POSTAL_CODE><COUNTRY VALUE="UK"/><PHONE>+44 1656642596</PHONE><URL>www.bridgend.gov.uk</URL></ADDRESS_REVIEW_BODY><DATE_DISPATCH_NOTICE>2019-09-09</DATE_DISPATCH_NOTICE></COMPLEMENTARY_INFO></F03_2014></FORM_SECTION></TED_EXPORT>