<?xml version="1.0" encoding="UTF-8"?><TED_EXPORT xmlns:xlink="http://www.w3.org/1999/xlink" xmlns:xsi="http://www.w3.org/2001/XMLSchema-instance" xmlns="http://publications.europa.eu/resource/schema/ted/R2.0.9/publication" xmlns:n2016="http://publications.europa.eu/resource/schema/ted/2016/nuts" xsi:schemaLocation="http://publications.europa.eu/resource/schema/ted/R2.0.9/publication TED_EXPORT.xsd" VERSION="R2.0.9.S03.E01" DOC_ID="424215-2019" EDITION="2019174"><TECHNICAL_SECTION><RECEPTION_ID>19-434682-001</RECEPTION_ID><DELETION_DATE>20200905</DELETION_DATE><FORM_LG_LIST>EN </FORM_LG_LIST><COMMENTS>From Convertor</COMMENTS></TECHNICAL_SECTION><LINKS_SECTION><XML_SCHEMA_DEFINITION_LINK xlink:type="simple" xlink:href="http://ted.europa.eu" xlink:title="TED WEBSITE"/><OFFICIAL_FORMS_LINK xlink:type="simple" xlink:href="http://ted.europa.eu"/><FORMS_LABELS_LINK xlink:type="simple" xlink:href="http://ted.europa.eu"/><ORIGINAL_CPV_LINK xlink:type="simple" xlink:href="http://ted.europa.eu"/><ORIGINAL_NUTS_LINK xlink:type="simple" xlink:href="http://ted.europa.eu"/></LINKS_SECTION><CODED_DATA_SECTION><REF_OJS><COLL_OJ>S</COLL_OJ><NO_OJ>174</NO_OJ><DATE_PUB>20190910</DATE_PUB></REF_OJS><NOTICE_DATA><NO_DOC_OJS>2019/S 174-424215</NO_DOC_OJS><URI_LIST><URI_DOC LG="EN">http://ted.europa.eu/udl?uri=TED:NOTICE:424215-2019:TEXT:EN:HTML</URI_DOC></URI_LIST><LG_ORIG>EN</LG_ORIG><ISO_COUNTRY VALUE="UK"/><IA_URL_GENERAL>https://www.retailenergycode.co.uk/</IA_URL_GENERAL><ORIGINAL_CPV CODE="79400000">Business and management consultancy and related services</ORIGINAL_CPV><ORIGINAL_CPV CODE="71314000">Energy and related services</ORIGINAL_CPV><ORIGINAL_CPV CODE="71314100">Electrical services</ORIGINAL_CPV><ORIGINAL_CPV CODE="71314200">Energy-management services</ORIGINAL_CPV><ORIGINAL_CPV CODE="71620000">Analysis services</ORIGINAL_CPV><ORIGINAL_CPV CODE="72253000">Helpdesk and support services</ORIGINAL_CPV><ORIGINAL_CPV CODE="72253100">Helpdesk services</ORIGINAL_CPV><ORIGINAL_CPV CODE="75112000">Administrative services for business operations</ORIGINAL_CPV><ORIGINAL_CPV CODE="72590000">Computer-related professional services</ORIGINAL_CPV><ORIGINAL_CPV CODE="79200000">Accounting, auditing and fiscal services</ORIGINAL_CPV><ORIGINAL_CPV CODE="79210000">Accounting and auditing services</ORIGINAL_CPV><ORIGINAL_CPV CODE="79212000">Auditing services</ORIGINAL_CPV><ORIGINAL_CPV CODE="79410000">Business and management consultancy services</ORIGINAL_CPV><ORIGINAL_CPV CODE="48000000">Software package and information systems</ORIGINAL_CPV><ORIGINAL_CPV CODE="48100000">Industry specific software package</ORIGINAL_CPV><ORIGINAL_CPV CODE="71621000">Technical analysis or consultancy services</ORIGINAL_CPV><ORIGINAL_CPV CODE="72000000">IT services: consulting, software development, Internet and support</ORIGINAL_CPV><ORIGINAL_CPV CODE="72212700">Software development services utilities</ORIGINAL_CPV><ORIGINAL_CPV CODE="71630000">Technical inspection and testing services</ORIGINAL_CPV><ORIGINAL_CPV CODE="72222300">Information technology services</ORIGINAL_CPV><ORIGINAL_CPV CODE="48700000">Software package utilities</ORIGINAL_CPV><n2016:PERFORMANCE_NUTS CODE="UKI">LONDON</n2016:PERFORMANCE_NUTS><n2016:CA_CE_NUTS CODE="UKI">LONDON</n2016:CA_CE_NUTS><VALUES><VALUE TYPE="ESTIMATED_TOTAL" CURRENCY="GBP">36000000.00</VALUE></VALUES></NOTICE_DATA><CODIF_DATA><DS_DATE_DISPATCH>20190906</DS_DATE_DISPATCH><AA_AUTHORITY_TYPE CODE="1">Ministry or any other national or federal authority</AA_AUTHORITY_TYPE><TD_DOCUMENT_TYPE CODE="0">Prior information notice without call for competition</TD_DOCUMENT_TYPE><NC_CONTRACT_NATURE CODE="4">Services</NC_CONTRACT_NATURE><PR_PROC CODE="9">Not applicable</PR_PROC><RP_REGULATION CODE="5">European Union, with participation by GPA countries</RP_REGULATION><TY_TYPE_BID CODE="9">Not applicable</TY_TYPE_BID><AC_AWARD_CRIT CODE="9">Not applicable</AC_AWARD_CRIT><MA_MAIN_ACTIVITIES CODE="S">General public services</MA_MAIN_ACTIVITIES><HEADING>01C01</HEADING><INITIATOR>01</INITIATOR></CODIF_DATA></CODED_DATA_SECTION><TRANSLATION_SECTION><ML_TITLES><ML_TI_DOC LG="BG"><TI_CY>Обединено кралство</TI_CY><TI_TOWN>Лондон</TI_TOWN><TI_TEXT><P>Консултантски услуги по управление и стопанска дейност и свързаните с тях услуги</P></TI_TEXT></ML_TI_DOC><ML_TI_DOC LG="CS"><TI_CY>Spojené království/Velká Británie</TI_CY><TI_TOWN>Londýn</TI_TOWN><TI_TEXT><P>Podnikatelské a manažerské poradenství a související služby</P></TI_TEXT></ML_TI_DOC><ML_TI_DOC LG="DA"><TI_CY>Forenede Kongerige, Det</TI_CY><TI_TOWN>London</TI_TOWN><TI_TEXT><P>Virksomhedsrådgivning og administrativ rådgivning samt beslægtede tjenesteydelser</P></TI_TEXT></ML_TI_DOC><ML_TI_DOC LG="DE"><TI_CY>das Vereinigte Königreich</TI_CY><TI_TOWN>London</TI_TOWN><TI_TEXT><P>Unternehmens- und Managementberatung und zugehörige Dienste</P></TI_TEXT></ML_TI_DOC><ML_TI_DOC LG="EL"><TI_CY>Ηνωμένο Βασίλειο</TI_CY><TI_TOWN>Λονδίνο</TI_TOWN><TI_TEXT><P>Υπηρεσίες παροχής γενικών επιχειρηματικών συμβουλών και συμβουλών σε θέματα διαχείρισης</P></TI_TEXT></ML_TI_DOC><ML_TI_DOC LG="EN"><TI_CY>United Kingdom</TI_CY><TI_TOWN>London</TI_TOWN><TI_TEXT><P>Business and management consultancy and related services</P></TI_TEXT></ML_TI_DOC><ML_TI_DOC LG="ES"><TI_CY>Reino Unido</TI_CY><TI_TOWN>Londres</TI_TOWN><TI_TEXT><P>Servicios de consultoría comercial y de gestión y servicios afines</P></TI_TEXT></ML_TI_DOC><ML_TI_DOC LG="ET"><TI_CY>Suurbritannia / Ühendkuningriik</TI_CY><TI_TOWN>London</TI_TOWN><TI_TEXT><P>Äri- ja juhtimisalased nõustamis- ja seonduvad teenused</P></TI_TEXT></ML_TI_DOC><ML_TI_DOC LG="FI"><TI_CY>Yhdistynyt kuningaskunta</TI_CY><TI_TOWN>Lontoo</TI_TOWN><TI_TEXT><P>Yrityskonsultointi, johdon konsultointi ja niihin liittyvät palvelut</P></TI_TEXT></ML_TI_DOC><ML_TI_DOC LG="FR"><TI_CY>Royaume-Uni</TI_CY><TI_TOWN>Londres</TI_TOWN><TI_TEXT><P>Conseil en affaires et en gestion et services connexes</P></TI_TEXT></ML_TI_DOC><ML_TI_DOC LG="GA"><TI_CY>Ríocht Aontaithe, an</TI_CY><TI_TOWN>Londain</TI_TOWN><TI_TEXT><P>Business and management consultancy and related services</P></TI_TEXT></ML_TI_DOC><ML_TI_DOC LG="HR"><TI_CY>Ujedinjena Kraljevina</TI_CY><TI_TOWN>London</TI_TOWN><TI_TEXT><P>Usluge savjetovanja na području poslovanja i upravljanja i srodne usluge</P></TI_TEXT></ML_TI_DOC><ML_TI_DOC LG="HU"><TI_CY>Egyesült Királyság</TI_CY><TI_TOWN>London</TI_TOWN><TI_TEXT><P>Üzleti és vezetői tanácsadói és kapcsolódó szolgáltatások</P></TI_TEXT></ML_TI_DOC><ML_TI_DOC LG="IT"><TI_CY>Regno Unito</TI_CY><TI_TOWN>Londra</TI_TOWN><TI_TEXT><P>Servizi di consulenza commerciale e di gestione e servizi connessi</P></TI_TEXT></ML_TI_DOC><ML_TI_DOC LG="LT"><TI_CY>Jungtinė Karalystė, Didžioji Britanija</TI_CY><TI_TOWN>Londonas</TI_TOWN><TI_TEXT><P>Verslo ir valdymo konsultacinės bei susijusios paslaugos</P></TI_TEXT></ML_TI_DOC><ML_TI_DOC LG="LV"><TI_CY>Apvienotā Karaliste</TI_CY><TI_TOWN>Londona</TI_TOWN><TI_TEXT><P>Uzņēmējdarbības un vadības konsultāciju un saistītie pakalpojumi</P></TI_TEXT></ML_TI_DOC><ML_TI_DOC LG="MT"><TI_CY>Ir-Renju Unit</TI_CY><TI_TOWN>Londra</TI_TOWN><TI_TEXT><P>Servizzi ta' l-amministrazzjoni tan-negozju u dawk relatati magħhom</P></TI_TEXT></ML_TI_DOC><ML_TI_DOC LG="NL"><TI_CY>Verenigd Koninkrijk</TI_CY><TI_TOWN>Londen</TI_TOWN><TI_TEXT><P>Adviezen inzake bedrijfsvoering en management, en aanverwante diensten</P></TI_TEXT></ML_TI_DOC><ML_TI_DOC LG="PL"><TI_CY>Zjednoczone Królestwo</TI_CY><TI_TOWN>Londyn</TI_TOWN><TI_TEXT><P>Usługi doradcze w zakresie działalności gospodarczej i zarządzania oraz podobne</P></TI_TEXT></ML_TI_DOC><ML_TI_DOC LG="PT"><TI_CY>Reino Unido</TI_CY><TI_TOWN>Londres</TI_TOWN><TI_TEXT><P>Serviços de consultoria em matéria comercial e de gestão e serviços conexos</P></TI_TEXT></ML_TI_DOC><ML_TI_DOC LG="RO"><TI_CY>Regatul Unit</TI_CY><TI_TOWN>Londra</TI_TOWN><TI_TEXT><P>Consultanţă în afaceri şi în management şi servicii conexe</P></TI_TEXT></ML_TI_DOC><ML_TI_DOC LG="SK"><TI_CY>Spojené kráľovstvo</TI_CY><TI_TOWN>Londýn</TI_TOWN><TI_TEXT><P>Poradenské služby v oblasti obchodu a riadenia a súvisiace služby (podnikateľské poradenstvo)</P></TI_TEXT></ML_TI_DOC><ML_TI_DOC LG="SL"><TI_CY>Združeno kraljestvo</TI_CY><TI_TOWN>London</TI_TOWN><TI_TEXT><P>Podjetniško in managersko svetovanje ter s tem povezane storitve</P></TI_TEXT></ML_TI_DOC><ML_TI_DOC LG="SV"><TI_CY>Förenade kungariket</TI_CY><TI_TOWN>London</TI_TOWN><TI_TEXT><P>Företags- och managementrådgivning samt tillhörande tjänster</P></TI_TEXT></ML_TI_DOC></ML_TITLES><ML_AA_NAMES><AA_NAME LG="EN">Retail Energy Code Company Ltd</AA_NAME></ML_AA_NAMES></TRANSLATION_SECTION><FORM_SECTION><F01_2014 CATEGORY="ORIGINAL" FORM="F01" LG="EN"><LEGAL_BASIS VALUE="32014L0024"/><NOTICE TYPE="PRI_ONLY"/><CONTRACTING_BODY><ADDRESS_CONTRACTING_BODY><OFFICIALNAME>Retail Energy Code Company Ltd</OFFICIALNAME><ADDRESS>130 Old Street</ADDRESS><TOWN>London</TOWN><POSTAL_CODE>EC1V 9BD</POSTAL_CODE><COUNTRY VALUE="UK"/><CONTACT_POINT>Fergus Alexander</CONTACT_POINT><PHONE>+44 7971078301</PHONE><E_MAIL>Procurement@retailenergycode.co.uk</E_MAIL><n2016:NUTS CODE="UKI"/><URL_GENERAL>https://www.retailenergycode.co.uk/</URL_GENERAL></ADDRESS_CONTRACTING_BODY><ADDRESS_FURTHER_INFO_IDEM/><CA_TYPE VALUE="MINISTRY"/><CA_ACTIVITY VALUE="GENERAL_PUBLIC_SERVICES"/></CONTRACTING_BODY><OBJECT_CONTRACT ITEM="1"><TITLE><P>Retail Energy Code — Code Management Services</P></TITLE><REFERENCE_NUMBER>TBC</REFERENCE_NUMBER><CPV_MAIN><CPV_CODE CODE="79400000"/></CPV_MAIN><TYPE_CONTRACT CTYPE="SERVICES"/><SHORT_DESCR><P>The Retail Energy Code Company is seeking providers with the appropriate experience to provide a range of services required for the new Retail Energy Code (REC). These are:</P><P>(a) REC performance assurance;</P><P>(b) REC professional services; and</P><P>(c) REC technical services functions.</P><P>The Retail Energy Code Company is the corporate vehicle created to enable the implementation of the Retail Energy Code in an effective, proper and efficient way.</P></SHORT_DESCR><VAL_ESTIMATED_TOTAL CURRENCY="GBP">36000000.00</VAL_ESTIMATED_TOTAL><LOT_DIVISION><LOT_COMBINING_CONTRACT_RIGHT><P>REC professional services and REC technical services.</P></LOT_COMBINING_CONTRACT_RIGHT></LOT_DIVISION><OBJECT_DESCR ITEM="1"><TITLE><P>REC Professional Services</P></TITLE><LOT_NO>1</LOT_NO><CPV_ADDITIONAL><CPV_CODE CODE="71314000"/></CPV_ADDITIONAL><CPV_ADDITIONAL><CPV_CODE CODE="71314100"/></CPV_ADDITIONAL><CPV_ADDITIONAL><CPV_CODE CODE="71314200"/></CPV_ADDITIONAL><CPV_ADDITIONAL><CPV_CODE CODE="71620000"/></CPV_ADDITIONAL><CPV_ADDITIONAL><CPV_CODE CODE="72253000"/></CPV_ADDITIONAL><CPV_ADDITIONAL><CPV_CODE CODE="72253100"/></CPV_ADDITIONAL><CPV_ADDITIONAL><CPV_CODE CODE="75112000"/></CPV_ADDITIONAL><CPV_ADDITIONAL><CPV_CODE CODE="72590000"/></CPV_ADDITIONAL><n2016:NUTS CODE="UKI"/><MAIN_SITE><P>London.</P></MAIN_SITE><SHORT_DESCR><P>The REC professional services provider will be the day-to-day manager of the REC, managing changes, stakeholders, and supporting the RECCo board to carry out its duties.</P><P>This will include account management through the provision of a helpdesk and training, proactive code party engagement, creation and management of a service portal, managing the change process for the Retail Energy Code and secretariat services as required by RECCo.</P></SHORT_DESCR></OBJECT_DESCR><OBJECT_DESCR ITEM="2"><TITLE><P>REC Performance Assurance</P></TITLE><LOT_NO>2</LOT_NO><CPV_ADDITIONAL><CPV_CODE CODE="71314000"/></CPV_ADDITIONAL><CPV_ADDITIONAL><CPV_CODE CODE="71314100"/></CPV_ADDITIONAL><CPV_ADDITIONAL><CPV_CODE CODE="71314200"/></CPV_ADDITIONAL><CPV_ADDITIONAL><CPV_CODE CODE="71620000"/></CPV_ADDITIONAL><CPV_ADDITIONAL><CPV_CODE CODE="79200000"/></CPV_ADDITIONAL><CPV_ADDITIONAL><CPV_CODE CODE="79210000"/></CPV_ADDITIONAL><CPV_ADDITIONAL><CPV_CODE CODE="79212000"/></CPV_ADDITIONAL><CPV_ADDITIONAL><CPV_CODE CODE="79400000"/></CPV_ADDITIONAL><CPV_ADDITIONAL><CPV_CODE CODE="79410000"/></CPV_ADDITIONAL><n2016:NUTS CODE="UKI"/><MAIN_SITE><P>London.</P></MAIN_SITE><SHORT_DESCR><P>The REC performance assurance provider will assess and assure performance of the code parties and the other lot providers.</P><P>It will produce a performance assurance framework and then implement and manage, maintain and update it over the life of the contract. It will manage the code party entry and exit process and conduct market monitoring and code party compliance audits.</P><P>It will assure code compliance and performance of the other lot providers.</P></SHORT_DESCR></OBJECT_DESCR><OBJECT_DESCR ITEM="3"><TITLE><P>REC Technical Services</P></TITLE><LOT_NO>3</LOT_NO><CPV_ADDITIONAL><CPV_CODE CODE="48000000"/></CPV_ADDITIONAL><CPV_ADDITIONAL><CPV_CODE CODE="48100000"/></CPV_ADDITIONAL><CPV_ADDITIONAL><CPV_CODE CODE="71621000"/></CPV_ADDITIONAL><CPV_ADDITIONAL><CPV_CODE CODE="72000000"/></CPV_ADDITIONAL><CPV_ADDITIONAL><CPV_CODE CODE="72212700"/></CPV_ADDITIONAL><CPV_ADDITIONAL><CPV_CODE CODE="79410000"/></CPV_ADDITIONAL><CPV_ADDITIONAL><CPV_CODE CODE="71630000"/></CPV_ADDITIONAL><CPV_ADDITIONAL><CPV_CODE CODE="72222300"/></CPV_ADDITIONAL><CPV_ADDITIONAL><CPV_CODE CODE="79400000"/></CPV_ADDITIONAL><CPV_ADDITIONAL><CPV_CODE CODE="71620000"/></CPV_ADDITIONAL><CPV_ADDITIONAL><CPV_CODE CODE="48700000"/></CPV_ADDITIONAL><CPV_ADDITIONAL><CPV_CODE CODE="71314000"/></CPV_ADDITIONAL><CPV_ADDITIONAL><CPV_CODE CODE="71314100"/></CPV_ADDITIONAL><CPV_ADDITIONAL><CPV_CODE CODE="71314200"/></CPV_ADDITIONAL><n2016:NUTS CODE="UKI"/><MAIN_SITE><P>London.</P></MAIN_SITE><SHORT_DESCR><P>The REC technical services provider will provide technical assurance, design authority and data management services.</P><P>As technical design authority, the provider will maintain integrity of the REC, technical documentations and products. It will manage data and data interfaces, provide technical assurance of code changes and provide technical support to code parties.</P></SHORT_DESCR></OBJECT_DESCR><DATE_PUBLICATION_NOTICE>2019-12-02</DATE_PUBLICATION_NOTICE></OBJECT_CONTRACT><PROCEDURE><CONTRACT_COVERED_GPA/></PROCEDURE><COMPLEMENTARY_INFO><INFO_ADD><P>It is planned to hold an early market engagement event to provide an opportunity to find out about this proposal.</P><P>Event: 11.9.2019 9.30 a.m.-11.30 a.m., Grosvenor Hotel, 101 Buckingham Palace Road, London, SW1W 0SJ.</P><P>To attend, please confirm attendance to Procurement@retailenergycode.co.uk</P></INFO_ADD><DATE_DISPATCH_NOTICE>2019-09-06</DATE_DISPATCH_NOTICE></COMPLEMENTARY_INFO></F01_2014></FORM_SECTION></TED_EXPORT>